{
  "version": 1,
  "bone_remap": {
    "Chest": ["Spine", "Spine2", "UpperChest"]
  },
  "clips": [
    {
      "action": "idle",
      "duration": 1.2,
      "loop": true,
      "tracks": [
        {
          "bone": "Spine",
          "keyframes": [
            { "t": 0.0, "rot": [0.0, 0.0, 0.0, 1.0] },
            { "t": 0.6, "rot": [0.02, 0.0, 0.0, 0.9998] },
            { "t": 1.2, "rot": [0.0, 0.0, 0.0, 1.0] }
          ]
        },
        {
          "bone": "Head",
          "keyframes": [
            { "t": 0.0, "rot": [0.0, 0.0, 0.0, 1.0] },
            { "t": 0.6, "rot": [-0.015, 0.01, 0.0, 0.9998] },
            { "t": 1.2, "rot": [0.0, 0.0, 0.0, 1.0] }
          ]
        }
      ]
    },
    {
      "action": "follow",
      "duration": 0.9,
      "loop": true,
      "tracks": [
        {
          "bone": "Spine",
          "keyframes": [
            { "t": 0.0, "rot": [-0.03, -0.05, 0.0, 0.9983] },
            { "t": 0.45, "rot": [-0.01, 0.06, 0.0, 0.9981] },
            { "t": 0.9, "rot": [-0.03, -0.05, 0.0, 0.9983] }
          ]
        },
        {
          "bone": "Head",
          "keyframes": [
            { "t": 0.0, "rot": [0.0, -0.08, 0.0, 0.9968] },
            { "t": 0.45, "rot": [0.0, 0.09, 0.0, 0.9959] },
            { "t": 0.9, "rot": [0.0, -0.08, 0.0, 0.9968] }
          ]
        }
      ]
    },
    {
      "action": "clickReact",
      "duration": 0.3,
      "loop": false,
      "tracks": [
        {
          "bone": "Chest",
          "keyframes": [
            { "t": 0.0, "scale": [1.0, 1.0, 1.0] },
            { "t": 0.08, "scale": [1.06, 0.92, 1.06] },
            { "t": 0.3, "scale": [1.0, 1.0, 1.0] }
          ]
        },
        {
          "bone": "Head",
          "keyframes": [
            { "t": 0.0, "rot": [-0.06, 0.0, 0.0, 0.9982] },
            { "t": 0.08, "rot": [0.04, 0.0, 0.0, 0.9992] },
            { "t": 0.3, "rot": [0.0, 0.0, 0.0, 1.0] }
          ]
        }
      ]
    },
    {
      "action": "drag",
      "duration": 0.6,
      "loop": true,
      "tracks": [
        {
          "bone": "Spine",
          "keyframes": [
            { "t": 0.0, "rot": [-0.10, 0.08, 0.0, 0.9918] },
            { "t": 0.3, "rot": [-0.14, -0.04, 0.0, 0.9894] },
            { "t": 0.6, "rot": [-0.10, 0.08, 0.0, 0.9918] }
          ]
        },
        {
          "bone": "Head",
          "keyframes": [
            { "t": 0.0, "rot": [0.03, 0.06, 0.0, 0.9978] },
            { "t": 0.3, "rot": [0.05, -0.06, 0.0, 0.9970] },
            { "t": 0.6, "rot": [0.03, 0.06, 0.0, 0.9978] }
          ]
        }
      ]
    },
    {
      "action": "hoverReact",
      "duration": 0.8,
      "loop": true,
      "tracks": [
        {
          "bone": "Spine",
          "keyframes": [
            { "t": 0.0, "rot": [-0.07, 0.18, 0.0, 0.9812] },
            { "t": 0.4, "rot": [0.05, -0.17, 0.0, 0.9842] },
            { "t": 0.8, "rot": [-0.07, 0.18, 0.0, 0.9812] }
          ]
        },
        {
          "bone": "Head",
          "keyframes": [
            { "t": 0.0, "rot": [0.10, 0.22, 0.0, 0.9704] },
            { "t": 0.4, "rot": [-0.08, -0.20, 0.0, 0.9766] },
            { "t": 0.8, "rot": [0.10, 0.22, 0.0, 0.9704] }
          ]
        }
      ]
    },
    {
      "action": "holdReact",
      "duration": 0.9,
      "loop": true,
      "tracks": [
        {
          "bone": "Spine",
          "keyframes": [
            { "t": 0.0, "rot": [-0.04, 0.00, 0.0, 0.9992], "scale": [1.0, 1.0, 1.0] },
            { "t": 0.45, "rot": [-0.17, 0.04, 0.0, 0.9846], "scale": [1.10, 0.78, 1.10] },
            { "t": 0.9, "rot": [-0.04, 0.00, 0.0, 0.9992], "scale": [1.0, 1.0, 1.0] }
          ]
        },
        {
          "bone": "Head",
          "keyframes": [
            { "t": 0.0, "rot": [-0.06, 0.00, 0.0, 0.9982] },
            { "t": 0.45, "rot": [-0.19, 0.03, 0.0, 0.9813] },
            { "t": 0.9, "rot": [-0.06, 0.00, 0.0, 0.9982] }
          ]
        }
      ]
    },
    {
      "action": "scrollReact",
      "duration": 0.36,
      "loop": false,
      "tracks": [
        {
          "bone": "Spine",
          "keyframes": [
            { "t": 0.0, "rot": [-0.02, 0.0, 0.0, 0.9998] },
            { "t": 0.09, "rot": [0.03, 0.27, 0.0, 0.9624] },
            { "t": 0.18, "rot": [-0.03, -0.25, 0.0, 0.9677] },
            { "t": 0.27, "rot": [0.02, 0.16, 0.0, 0.9869] },
            { "t": 0.36, "rot": [0.0, 0.0, 0.0, 1.0] }
          ]
        },
        {
          "bone": "Head",
          "keyframes": [
            { "t": 0.0, "rot": [0.0, 0.0, 0.0, 1.0] },
            { "t": 0.09, "rot": [0.02, 0.31, 0.0, 0.9505] },
            { "t": 0.18, "rot": [-0.02, -0.29, 0.0, 0.9568] },
            { "t": 0.27, "rot": [0.01, 0.19, 0.0, 0.9817] },
            { "t": 0.36, "rot": [0.0, 0.0, 0.0, 1.0] }
          ]
        }
      ]
    }
  ]
}
